CHANGELOG.txt
LICENSE.txt
MANIFEST.in
README.rst
pyproject.toml
setup.cfg
setup.py
tox.ini
src/metadata_parser/__init__.py
src/metadata_parser/config.py
src/metadata_parser/exceptions.py
src/metadata_parser/py.typed
src/metadata_parser/regex.py
src/metadata_parser/requests_extensions.py
src/metadata_parser/typing.py
src/metadata_parser/utils.py
src/metadata_parser.egg-info/PKG-INFO
src/metadata_parser.egg-info/SOURCES.txt
src/metadata_parser.egg-info/dependency_links.txt
src/metadata_parser.egg-info/not-zip-safe
src/metadata_parser.egg-info/requires.txt
src/metadata_parser.egg-info/top_level.txt
tests/__init__.py
tests/test_document_parsing.py
tests/test_ip_tracking.py
tests/test_responses.py
tests/test_sessions.py
tests/test_url_parsing.py
tests/html_scaffolds/charset_a.html
tests/html_scaffolds/charset_b.html
tests/html_scaffolds/charset_c.html
tests/html_scaffolds/duplicates.html
tests/html_scaffolds/simple.html