Metadata-Version: 2.4
Name: metadata_parser
Version: 1.0.0
Summary: A module to parse metadata out of urls and html documents
Home-page: https://github.com/jvanasco/metadata_parser
Author: Jonathan Vanasco
Author-email: jonathan@findmeon.com
License: MIT
Keywords: opengraph protocol facebook
Classifier: Intended Audience :: Developers
Classifier: Programming Language :: Python :: 3
Classifier: Programming Language :: Python :: 3.7
Classifier: Programming Language :: Python :: 3.8
Classifier: Programming Language :: Python :: 3.9
Classifier: Programming Language :: Python :: 3.10
Classifier: Programming Language :: Python :: 3.11
Classifier: Programming Language :: Python :: 3.12
Classifier: Programming Language :: Python :: 3.13
Classifier: Topic :: Text Processing :: Markup :: HTML
Classifier: Topic :: Software Development :: Libraries :: Python Modules
License-File: LICENSE.txt
Requires-Dist: BeautifulSoup4<4.14.0,>4.13.0
Requires-Dist: requests>=2.19.1
Requires-Dist: requests-toolbelt>=0.8.0
Requires-Dist: tldextract<6.0.0
Requires-Dist: typing_extensions
Provides-Extra: testing
Requires-Dist: httpbin; extra == "testing"
Requires-Dist: flake8; extra == "testing"
Requires-Dist: flake8-import-order>=0.19.2; extra == "testing"
Requires-Dist: pytest; extra == "testing"
Requires-Dist: pytest-httpbin; extra == "testing"
Requires-Dist: responses; extra == "testing"
Requires-Dist: types-beautifulsoup4; extra == "testing"
Requires-Dist: types-requests; extra == "testing"
Requires-Dist: werkzeug<2.1.0; extra == "testing"
Dynamic: author
Dynamic: author-email
Dynamic: classifier
Dynamic: description
Dynamic: home-page
Dynamic: keywords
Dynamic: license
Dynamic: license-file
Dynamic: provides-extra
Dynamic: requires-dist
Dynamic: summary
